setup.py
django_versionfield3.egg-info/PKG-INFO
django_versionfield3.egg-info/SOURCES.txt
django_versionfield3.egg-info/dependency_links.txt
django_versionfield3.egg-info/pbr.json
django_versionfield3.egg-info/requires.txt
django_versionfield3.egg-info/top_level.txt
versionfield/__init__.py
versionfield/constants.py
versionfield/forms.py
versionfield/models.py
versionfield/utils.py
versionfield/version.py