Metadata-Version: 1.1
Name: django-versionfield3
Version: 0.1.3
Summary: A DB Independent Custom Django Field for storing Version numbers for fast indexing
Home-page: https://github.com/Crystalnix/django-versionfield3
Author: Egor Yurtaev
Author-email: yurtaev.egor+versionfield@gmail.com
License: BSD
Platform: UNKNOWN
Classifier: Development Status :: 5 - Production/Stable
Classifier: Framework :: Django
Classifier: Intended Audience :: Developers
Classifier: License :: OSI Approved :: BSD License
Classifier: Operating System :: OS Independent
Classifier: Programming Language :: Python
Classifier: Programming Language :: Python :: 2
Classifier: Programming Language :: Python :: 2.7
Classifier: Programming Language :: Python :: 3
Classifier: Programming Language :: Python :: 3.2
Classifier: Programming Language :: Python :: 3.3
Classifier: Programming Language :: Python :: 3.4
Classifier: Topic :: Internet :: WWW/HTTP
